aiocache_dynamodb/__init__.py
aiocache_dynamodb/constants.py
aiocache_dynamodb/dynamodb.py
aiocache_dynamodb/exceptions.py
aiocache_dynamodb/py.typed
aiocache_dynamodb/utils.py
aiocache_dynamodb-1.1.2.dist-info/METADATA
aiocache_dynamodb-1.1.2.dist-info/WHEEL
aiocache_dynamodb-1.1.2.dist-info/licenses/LICENSE
aiocache_dynamodb-1.1.2.dist-info/RECORD
