Metadata-Version: 2.4
Name: aiocache-dynamodb
Version: 1.1.2
Summary: AioCache DynamoDB Backend using Aiobotocore
Project-URL: source, https://github.com/vonsteer/aiocache-dynamodb
License: MIT License
License-File: LICENSE
Keywords: aiobotocore,aiocache,asyncio,aws,backend,cache,dynamodb
Classifier: Development Status :: 5 - Production/Stable
Classifier: Framework :: AsyncIO
Classifier: Intended Audience :: Developers
Classifier: Intended Audience :: Information Technology
Classifier: License :: OSI Approved :: MIT License
Classifier: Natural Language :: English
Classifier: Operating System :: OS Independent
Classifier: Programming Language :: Python
Classifier: Programming Language :: Python :: 3
Classifier: Programming Language :: Python :: 3 :: Only
Classifier: Programming Language :: Python :: 3.10
Classifier: Programming Language :: Python :: 3.11
Classifier: Programming Language :: Python :: 3.12
Classifier: Programming Language :: Python :: 3.13
Classifier: Topic :: Software Development
Classifier: Topic :: Software Development :: Libraries
Classifier: Topic :: Software Development :: Libraries :: Python Modules
Classifier: Topic :: System :: Networking
Classifier: Typing :: Typed
Requires-Python: >=3.10
Requires-Dist: aiobotocore>=2.21.1
Requires-Dist: aiocache>=0.12.3
Requires-Dist: botocore>=1.37.1
